{
  "users": [
    {
      "id": 1,
      "name": "张三"
    },
    {
      "id": 2,
      "name": "李四"
    },
    {
      "id": 3,
      "name": "王五"
    },
    {
      "id": 4,
      "name": "赵六"
    }
  ],
  "projects": [
    {
      "id": 1,
      "name": "骑手管理",
      "personId": 1,
      "organization": "外卖组"
    },
    {
      "id": 2,
      "name": "团购APP",
      "personId": 2,
      "organization": "团购组"
    },
    {
      "id": 3,
      "name": "物料管理系统",
      "personId": 2,
      "organization": "物料组"
    },
    {
      "id": 4,
      "name": "总部管理系统",
      "personId": 3,
      "organization": "总部组"
    },
    {
      "id": 5,
      "name": "送餐路线规划系统",
      "personId": 4,
      "organization": "送餐组"
    }
  ]
}